gitlab_c_function_content_mcp/__init__.py
gitlab_c_function_content_mcp/main.py
gitlab_c_function_content_mcp-0.1.5.dist-info/METADATA
gitlab_c_function_content_mcp-0.1.5.dist-info/WHEEL
gitlab_c_function_content_mcp-0.1.5.dist-info/entry_points.txt
gitlab_c_function_content_mcp-0.1.5.dist-info/top_level.txt
gitlab_c_function_content_mcp-0.1.5.dist-info/RECORD
