Metadata-Version: 2.4
Name: gitlab-c-function-content-mcp
Version: 0.1.5
Summary: Add your description here
Requires-Python: >=3.12
Requires-Dist: mcp[cli]>=1.20.0
Requires-Dist: requests>=2.32.5
Requires-Dist: tree-sitter>=0.25.2
Requires-Dist: tree-sitter-c>=0.24.1
